easygit/__init__.py
easygit/__main__.py
easygit/commands/__init__.py
easygit/commands/add.py
easygit/commands/branch.py
easygit/commands/checkout.py
easygit/commands/clone.py
easygit/commands/commit.py
easygit/commands/diff.py
easygit/commands/init.py
easygit/commands/log.py
easygit/commands/pull.py
easygit/commands/push.py
easygit/commands/remote.py
easygit/commands/status.py
easygit/core/__init__.py
easygit/core/color.py
easygit/core/commands.py
easygit/core/config.py
easygit/core/git.py
easygit/core/utils.py
git_simplified-1.0.4.dist-info/METADATA
git_simplified-1.0.4.dist-info/WHEEL
git_simplified-1.0.4.dist-info/entry_points.txt
git_simplified-1.0.4.dist-info/top_level.txt
git_simplified-1.0.4.dist-info/RECORD
