Metadata-Version: 2.4
Name: git-simplified
Version: 1.0.4
Summary: A beginner-friendly Git CLI with colorful output
Home-page: https://github.com/QinCai-rui/easygit
Author: QinCai-rui
Author-email: raymontqin_rui@outlook.com
Classifier: Programming Language :: Python :: 3
Classifier: License :: OSI Approved :: MIT License
Classifier: Operating System :: OS Independent
Requires-Python: >=3.6
Requires-Dist: colorama
Dynamic: author
Dynamic: author-email
Dynamic: classifier
Dynamic: description-content-type
Dynamic: home-page
Dynamic: requires-dist
Dynamic: requires-python
Dynamic: summary
